nodelib/__init__.py
nodelib/bsc.py
nodelib/ether.py
nodelib/exceptions.py
nodelib/factory.py
nodelib/interface.py
nodelib/tron.py
nodelib/types/__init__.py
nodelib/types/block.py
nodelib/types/receipt.py
nodelib/types/transfer.py
nodelib-0.2.0.dist-info/WHEEL
nodelib-0.2.0.dist-info/METADATA
nodelib-0.2.0.dist-info/RECORD
